lpmalgos.cpython-312-x86_64-linux-gnu.so
lpm.cpython-312-x86_64-linux-gnu.so
lpm/__init__.py
lpmalgos-1.1.5.dist-info/RECORD
lpmalgos-1.1.5.dist-info/METADATA
lpmalgos-1.1.5.dist-info/top_level.txt
lpmalgos-1.1.5.dist-info/WHEEL
lpmalgos.libs/libgomp-a34b3233.so.1.0.0
