Metadata-Version: 2.1
Name: lpmalgos
Version: 1.1.5
Summary: lpmalgos
Home-page: https://newavesoft.com
Author: Péricles Lopes Machado
Author-email: pericles@newavesoft.com
Classifier: Programming Language :: Python :: 3.12
Requires-Dist: numpy
Requires-Dist: colorlover
Requires-Dist: pandas
Requires-Dist: plotly
Requires-Dist: jsonschema
